arborlife/__init__.py
arborlife/config.py
arborlife/forest.py
arborlife/soil.py
arborlife/tile.py
arborlife/tree.py
arborlife/version.py
arborlife/config/arborlife.yml
tests/__init__.py
tests/test_forest.py
tests/test_soil.py
tests/test_tile.py
tests/test_tree.py
arborlife-0.1.4.dist-info/LICENSE
arborlife-0.1.4.dist-info/METADATA
arborlife-0.1.4.dist-info/WHEEL
arborlife-0.1.4.dist-info/top_level.txt
arborlife-0.1.4.dist-info/RECORD
